datasette_sqlite_vec/__init__.py
datasette_sqlite_vec-0.1.6.dist-info/METADATA
datasette_sqlite_vec-0.1.6.dist-info/WHEEL
datasette_sqlite_vec-0.1.6.dist-info/entry_points.txt
datasette_sqlite_vec-0.1.6.dist-info/top_level.txt
datasette_sqlite_vec-0.1.6.dist-info/RECORD
